{
  "gitSyncId": "693476e8bab1731f64a493f4_64101354-d615-46ca-b6e0-ed555757b3fc",
  "id": "EXPORTACIONES_qCpTiposRemolqueDropdown",
  "pluginId": "postgres-plugin",
  "pluginType": "DB",
  "unpublishedAction": {
    "actionConfiguration": {
      "body": "select\n  id as value,\n  upper(nombre) as label,\n  codigo\nfrom public.tipos_remolque\nwhere activo = true\norder by sort_order nulls last, nombre;",
      "encodeParamsToggle": true,
      "paginationType": "NONE",
      "pluginSpecifiedTemplates": [
        {
          "value": true
        }
      ],
      "timeoutInMillisecond": 10000
    },
    "confirmBeforeExecute": false,
    "datasource": {
      "id": "supabase_comex",
      "isAutoGenerated": false,
      "name": "supabase_comex",
      "pluginId": "postgres-plugin"
    },
    "dynamicBindingPathList": [],
    "name": "qCpTiposRemolqueDropdown",
    "pageId": "EXPORTACIONES",
    "runBehaviour": "AUTOMATIC",
    "userSetOnLoad": false
  }
}