{
  "gitSyncId": "693476e8bab1731f64a493f4_57ea6593-6c1e-457d-a014-7ad6d859cea1",
  "id": "EXPORTACIONES_qCvItemEmpaqueDropdown",
  "pluginId": "postgres-plugin",
  "pluginType": "DB",
  "unpublishedAction": {
    "actionConfiguration": {
      "body": "select\n  pe.id::text as value,\n  upper(pe.nombre || ' - ' || coalesce(pe.presentacion_comercial, '')) as label,\n\n  pe.id::text as empaque_id,\n  upper(pe.codigo) as codigo_empaque,\n  upper(pe.nombre) as nombre_empaque,\n  upper(coalesce(pe.presentacion_comercial, '')) as presentacion_comercial,\n  upper(pe.tipo_empaque) as tipo_empaque,\n  upper(pe.unidad_comercial) as unidad_comercial,\n  upper(coalesce(pe.unidad_dian, '')) as unidad_dian,\n\n  coalesce(pe.cantidad_por_empaque, 1) as cantidad_por_empaque,\n  coalesce(pe.peso_neto_empaque_kg, 0) as peso_neto_empaque_kg,\n  coalesce(pe.peso_bruto_empaque_kg, 0) as peso_bruto_empaque_kg,\n  coalesce(pe.volumen_empaque_m3, 0) as volumen_empaque_m3,\n  pe.es_empaque_default\nfrom public.producto_empaques pe\nwhere pe.activo = true\n  and pe.producto_id::text = '{{ slCvItemCodigo.selectedOptionValue || \"\" }}'\norder by pe.es_empaque_default desc, pe.nombre;",
      "encodeParamsToggle": true,
      "paginationType": "NONE",
      "pluginSpecifiedTemplates": [
        {
          "value": true
        }
      ],
      "timeoutInMillisecond": 10000
    },
    "confirmBeforeExecute": false,
    "datasource": {
      "id": "supabase_comex",
      "isAutoGenerated": false,
      "name": "supabase_comex",
      "pluginId": "postgres-plugin"
    },
    "dynamicBindingPathList": [
      {
        "key": "body"
      }
    ],
    "name": "qCvItemEmpaqueDropdown",
    "pageId": "EXPORTACIONES",
    "runBehaviour": "AUTOMATIC",
    "userSetOnLoad": false
  }
}